senstile_utils/__init__.py
senstile_utils/config/__init__.py
senstile_utils/event/__init__.py
senstile_utils/observer/__init__.py
senstile_utils/retry/__init__.py
senstile_utils/retry/retry_exception.py
senstile_utils-0.1.7.dist-info/LICENSE
senstile_utils-0.1.7.dist-info/METADATA
senstile_utils-0.1.7.dist-info/WHEEL
senstile_utils-0.1.7.dist-info/top_level.txt
senstile_utils-0.1.7.dist-info/RECORD
