Metadata-Version: 2.1
Name: senstile-utils
Version: 0.1.7
Summary: A set of common utils modules and functions for Senstile Python Api development
Author-email: Jose Alejandro Concepcion Alvarez <pepe@senstile.com>
License: MIT License
Project-URL: Home Page, https://gitlab.com/senstile_tech/senstile_python_packages/senstile_utils/-/blob/master/README.MD
Classifier: Programming Language :: Python :: 3
Classifier: License :: OSI Approved :: MIT License
Classifier: Operating System :: OS Independent
Requires-Python: >=3.7
License-File: LICENSE
Requires-Dist: toml
Provides-Extra: dev
Requires-Dist: pytest ; extra == 'dev'
Requires-Dist: requests ; extra == 'dev'
Requires-Dist: pytest-asyncio ; extra == 'dev'
